{
  "seo": {
    "title": "Trem, MRT, & LRT: Transportasi Rel Masa Depan Indonesia",
    "desc": "Transportasi berbasis rel adalah sarana angkutan yang rodanya didesain berjalan di atas rel. Karena berjalan di atas rel, hambatan daya gesek pun lebih rendah daripada moda darat lainnya yang membuat perpindahan angkutan yang membawa barang dan manusia dari satu titik ke titik lain menjadi lebih cepat.",
    "image": "/assets/trem-mrt-lrt-transportasi-rel-masa-depan-indonesia/mrt-cover.png",
    "publishedAt": "12/11/2024"
  },
  "title": "Trem, MRT, & LRT: Transportasi Rel Masa Depan Indonesia",
  "slug": "trem-mrt-lrt-transportasi-rel-masa-depan-indonesia",
  "credits": {
    "editors": "Aulli Reza Atmam",
    "writers": "Aslamatur Rizqiyah, Afdal Hasan, Muhammad Fazer Mileneo, Firdarainy Nuril Izzah, Rizky Kusumo",
    "designers": "Arco Pradipta, Ario Priagung Nugroho",
    "developers": "Danar Widi Utomo, Fika Nur Aini"
  }
}